fancylists/__init__.py
fancylists/fancylists.py
pymdown_fancylists-0.4.0.dist-info/METADATA
pymdown_fancylists-0.4.0.dist-info/WHEEL
pymdown_fancylists-0.4.0.dist-info/top_level.txt
pymdown_fancylists-0.4.0.dist-info/RECORD
