Metadata-Version: 2.1
Name: pymdown-fancylists
Version: 0.4.0
Summary: Python Markdown Extension that allows more types of lists.
Author-email: Joan Puigcerver <joapuiib@gmail.com>
License: MIT
Project-URL: Homepage, https://github.com/joapuiib/pymdown-fancylists
Project-URL: Repository, https://github.com/joapuiib/pymdown-fancylists
Keywords: extensions,markdown
Requires-Python: >=3.8
Requires-Dist: Markdown >=3.6
